proj/__init__.py
proj/asgi.py
proj/settings.py
proj/urls.py
proj/wsgi.py
pubsub_event_store/__init__.py
pubsub_event_store/admin.py
pubsub_event_store/models.py
pubsub_event_store/serializers.py
pubsub_event_store/utils.py
pubsub_event_store/migrations/0001_initial.py
pubsub_event_store/migrations/0002_auto_20220218_0556.py
pubsub_event_store/migrations/__init__.py
pubsub_event_store-0.0.4.dist-info/METADATA
pubsub_event_store-0.0.4.dist-info/WHEEL
pubsub_event_store-0.0.4.dist-info/top_level.txt
pubsub_event_store-0.0.4.dist-info/RECORD
