Metadata-Version: 2.1
Name: pubsub-event-store
Version: 0.0.4
Summary: Saving event details to be able to replay them
Home-page: https://github.com/Anmol-Porwal18/pubsub_event_store
Author: Anmol Porwal
Author-email: anmolporwal@ymail.com
License: MIT
Keywords: events,rabbitmq,replay events,pubsub
Platform: any
Classifier: Programming Language :: Python :: 3.7
Classifier: License :: OSI Approved :: MIT License
Classifier: Operating System :: OS Independent
Requires-Python: >=3.7
Requires-Dist: django (>=3.2.11)
Requires-Dist: django-model-utils (>=4.0.0)
Requires-Dist: djangorestframework (>=3.11.2)
Requires-Dist: django-environ (>=0.4.5)
